{
	"d": {
		"results": [{
			"__metadata": {
				"id": "https://eq1.evorait.net:50103/sap/opu/odata/EVORA/EO_MAIN_SRV/NetworkSet('827963_0010')",
				"uri": "https://eq1.evorait.net:50103/sap/opu/odata/EVORA/EO_MAIN_SRV/NetworkSet('827963_0010')",
				"type": "com.evorait.evoorderrelate.Network"
			},
			"NETWORK_ID": "827963_0010"
		},{
			"__metadata": {
				"id": "https://eq1.evorait.net:50103/sap/opu/odata/EVORA/EO_MAIN_SRV/NetworkSet('827963_0010')",
				"uri": "https://eq1.evorait.net:50103/sap/opu/odata/EVORA/EO_MAIN_SRV/NetworkSet('827963_0010')",
				"type": "com.evorait.evoorderrelate.Network"
			},
			"NETWORK_ID": "827964_0010"
		},{
			"__metadata": {
				"id": "https://eq1.evorait.net:50103/sap/opu/odata/EVORA/EO_MAIN_SRV/NetworkSet('827963_0010')",
				"uri": "https://eq1.evorait.net:50103/sap/opu/odata/EVORA/EO_MAIN_SRV/NetworkSet('827963_0010')",
				"type": "com.evorait.evoorderrelate.Network"
			},
			"NETWORK_ID": "827965_0010"
		}]
	}
}